Workbook

Sheet Comps Summary
A1: Indian IT Services — DCF Valuation Comparison (Current, Jul 2026)
A3: Metric | B3: TCS | C3: Infosys | D3: HCLTech
A4: WACC | B4: =Assumptions!B36 -> 0.12368358 | C4: =Assumptions!C36 -> 0.12567962 | D4: =Assumptions!D36 -> 0.12243193
A5: Enterprise Value (₹ Cr) | B5: ='DCF - TCS'!B29 -> 799807.96 | C5: ='DCF - Infosys'!B29 -> 395519.58 | D5: ='DCF - HCLTech'!B29 -> 255621.67
A6: Equity Value (₹ Cr) | B6: ='DCF - TCS'!B31 -> 822512.96 | C6: ='DCF - Infosys'!B31 -> 409519.58 | D6: ='DCF - HCLTech'!B31 -> 265121.67
A7: Implied Value per Share (₹) | B7: ='DCF - TCS'!B33 -> 2273.3913 | C7: ='DCF - Infosys'!B33 -> 994.94554 | D7: ='DCF - HCLTech'!B33 -> 976.86689
A8: Current Share Price (₹, Jul 2026) | B8: ='DCF - TCS'!B34 -> 2069 | C8: ='DCF - Infosys'!B34 -> 1053 | D8: ='DCF - HCLTech'!B34 -> 1150
A9: Implied Upside / (Downside) | B9: ='DCF - TCS'!B35 -> 0.098787467 | C9: ='DCF - Infosys'!B35 -> -0.05513244 | D9: ='DCF - HCLTech'!B35 -> -0.15055053
A10: EV / FY26A EBIT (x) | B10: ='DCF - TCS'!B29/Assumptions!B20/Assumptions!B21 -> 11.052767 | C10: ='DCF - Infosys'!B29/Assumptions!C20/Assumptions!C21 -> 10.906086 | D10: ='DCF - HCLTech'!B29/Assumptions!D20/Assumptions!D21 -> 10.940093
A11: FY26A EBIT Margin | B11: =Assumptions!B21 -> 0.271 | C11: =Assumptions!C21 -> 0.203 | D11: =Assumptions!D21 -> 0.179
A13: All three companies use identical methodology (WACC via CAPM, 5-yr FCFF projection, Gordon Growth terminal value with the same 5% terminal growth and 25% tax rate) so relative valuation differences reflect company-specific inputs (growth, margin, beta, capital structure) rather than modeling inconsistency. See each company's DCF tab for full build-up; see Assumptions tab for all inputs and sources.

Sheet Assumptions
A1: Indian IT Services — 3-Company DCF Model: Assumptions (Current, as of Jul 2026)
A3: Shared Macro & Methodology Assumptions (applied to all 3 companies)
A4: Risk-Free Rate (India 10Y G-Sec, Jul 2026) | B4: 0.0675 | C4: Source: Trading Economics, India 10Y bond yield, Jul 2026
A5: Equity Risk Premium — India | B5: 0.065 | C5: Illustrative estimate (Damodaran-style country ERP)
A6: Effective Tax Rate (all 3 companies) | B6: 0.25 | C6: Typical effective rate for large Indian IT exporters
A7: Pre-Tax Cost of Debt (all 3 companies) | B7: 0.075 | C7: Assumed ~AAA Indian corporate bond yield
A8: D&A (% of Revenue, all 3) | B8: 0.021 | C8: Consistent methodology across peers for comparability
A9: Capex (% of Revenue, all 3) | B9: 0.022
A10: Incremental NWC (% of ΔRevenue, all 3) | B10: 0.08
A11: Terminal Growth Rate (g, all 3) | B11: 0.05 | C11: Conservative — below long-run nominal GDP growth & Rf
A13: Company-Specific Inputs (Current — Latest Audited FY & Live Market Data, Jul 2026)
A14: Metric | B14: TCS | C14: Infosys | D14: HCLTech
A15: Current Share Price (₹) | B15: 2069 | C15: 1053 | D15: 1150 | E15: Source: NSE/Yahoo Finance, close prices, Jul 2026
A16: Shares Outstanding (Cr) | B16: 361.8 | C16: 411.6 | D16: 271.4 | E16: TCS/Infosys: co. filings & market cap cross-check; HCLTech: derived from FY26 Net Profit / EPS
A17: Levered Beta (5-Year) | B17: 0.88 | C17: 0.9 | D17: 0.85 | E17: TCS: Morningstar 5Y beta; Infosys/HCLTech: approximate, similar low-beta IT peer profile
A18: Total Debt (₹ Cr, FY26) | B18: 11283 | C18: 2000 | D18: 1500 | E18: TCS: FY26 Consolidated Balance Sheet; Infosys/HCLTech approximate — both are near debt-free
A19: Cash & Investments (₹ Cr, FY26) | B19: 33988 | C19: 16000 | D19: 11000 | E19: TCS: FY26 Consolidated Balance Sheet; Infosys/HCLTech approximate
A20: Base Year Revenue — FY26A (₹ Cr) | B20: 267021 | C20: 178650 | D20: 130534 | E20: FY26 Consolidated P&L (audited, year ended Mar 2026); HCLTech derived from reported Net Income as % of revenue
A21: EBIT Margin (FY26A, held constant) | B21: 0.271 | C21: 0.203 | D21: 0.179 | E21: FY26 Operating Profit / Revenue (HCLTech: normalized, excl. one-time Labour Code charge)
A22: Revenue Growth — Year 1 | B22: 0.07 | C22: 0.08 | D22: 0.07
A23: Revenue Growth — Year 2 | B23: 0.07 | C23: 0.075 | D23: 0.065
A24: Revenue Growth — Year 3 | B24: 0.065 | C24: 0.07 | D24: 0.06
A25: Revenue Growth — Year 4 | B25: 0.06 | C25: 0.065 | D25: 0.055
A26: Revenue Growth — Year 5 | B26: 0.055 | C26: 0.06 | D26: 0.05
A28: Derived: Market Cap, Cost of Capital (WACC)
A29: Metric | B29: TCS | C29: Infosys | D29: HCLTech
A30: Market Capitalization (₹ Cr) | B30: =B15*B16 -> 748564.2 | C30: =C15*C16 -> 433414.8 | D30: =D15*D16 -> 312110
A31: Net Debt / (Net Cash) (₹ Cr) | B31: =B18-B19 -> -22705 | C31: =C18-C19 -> -14000 | D31: =D18-D19 -> -9500
A32: Cost of Equity (Ke = Rf + β × ERP) | B32: =$B$4+B17*$B$5 -> 0.1247 | C32: =$B$4+C17*$B$5 -> 0.126 | D32: =$B$4+D17*$B$5 -> 0.12275
A33: After-Tax Cost of Debt | B33: =$B$7*(1-$B$6) -> 0.05625 | C33: =$B$7*(1-$B$6) -> 0.05625 | D33: =$B$7*(1-$B$6) -> 0.05625
A34: Weight of Equity — E/(D+E) | B34: =B30/(B30+B18) -> 0.98515096 | C34: =C30/(C30+C18) -> 0.99540668 | D34: =D30/(D30+D18) -> 0.99521699
A35: Weight of Debt — D/(D+E) | B35: =B18/(B30+B18) -> 0.014849038 | C35: =C18/(C30+C18) -> 0.0045933211 | D35: =D18/(D30+D18) -> 0.0047830107
A36: WACC | B36: =B34*B32+B35*B33 -> 0.12368358 | C36: =C34*C32+C35*C33 -> 0.12567962 | D36: =D34*D32+D35*D33 -> 0.12243193
A38: Share prices are live/current (Jul 2026), directly verifiable via NSE/Yahoo Finance. TCS financials and balance sheet figures are from audited FY26 filings. Debt/cash figures for Infosys and HCLTech are reasonable estimates (both are near debt-free), not exact filings — flagged for follow-up if precision matters. Blue = hardcoded input. Black = formula. Model built for educational/portfolio purposes; not investment advice.

Sheet Historicals
A1: TCS / Infosys / HCLTech — Recent Financials (Consolidated, ₹ Crores, FY ended March, FY23-FY26)
A3: TCS
A4: Metric | B4: FY2023 | C4: FY2024 | D4: FY2025 | E4: FY2026
A5: Revenue | B5: 225458 | C5: 240893 | D5: 255324 | E5: 267021
A6: EBIT (Operating Profit) | B6: 59259 | C6: 64296 | D6: 67407 | E6: 72398
A7: EBIT Margin % | B7: =B6/B5 -> 0.26283831 | C7: =C6/C5 -> 0.26690688 | D7: =D6/D5 -> 0.26400573 | E7: =E6/E5 -> 0.27113223
A8: Net Profit | B8: 42303 | C8: 46099 | D8: 48797 | E8: 49454
A9: Revenue Growth % (YoY) | C9: =C5/B5-1 -> 0.068460645 | D9: =D5/C5-1 -> 0.059906265 | E9: =E5/D5-1 -> 0.04581238
A11: Infosys
A12: Metric | B12: FY2023 | C12: FY2024 | D12: FY2025 | E12: FY2026
A13: Revenue | B13: 146767 | C13: 153670 | D13: 162990 | E13: 178650
A14: EBIT (Operating Profit) | B14: 32157 | C14: 32754 | D14: 34424 | E14: 36254
A15: EBIT Margin % | B15: =B14/B13 -> 0.21910239 | C15: =C14/C13 -> 0.21314505 | D15: =D14/D13 -> 0.21120314 | E15: =E14/E13 -> 0.20293311
A16: Net Profit | B16: 24095 | C16: 24108 | D16: 26750 | E16: 29474
A17: Revenue Growth % (YoY) | C17: =C13/B13-1 -> 0.047033734 | D17: =D13/C13-1 -> 0.060649444 | E17: =E13/D13-1 -> 0.096079514
A19: HCLTech
A20: Metric | B20: FY2023 | C20: FY2024 | D20: FY2025 | E20: FY2026
A21: Revenue | B21: 101456 | C21: 109913 | D21: 117055 | E21: 130534
A22: EBIT (Operating Profit) | B22: 18708 | C22: 20015 | D22: 21420 | E22: 23366
A23: EBIT Margin % | B23: =B22/B21 -> 0.18439521 | C23: =C22/C21 -> 0.18209857 | D23: =D22/D21 -> 0.1829909 | E23: =E22/E21 -> 0.17900317
A24: Net Profit | B24: 14846 | C24: 15132 | D24: 17390 | E24: 17361
A25: Revenue Growth % (YoY) | C25: =C21/B21-1 -> 0.083356332 | D25: =D21/C21-1 -> 0.064978665 | E25: =E21/D21-1 -> 0.115151
A27: Source: Company FY26 (year ended March 2026) and prior-year investor releases, and Screener.in consolidated financials, accessed July 2026. HCLTech FY26 figures normalized to exclude one-time Labour Code charge.

Sheet DCF - TCS
A1: TCS — Discounted Cash Flow (DCF) Model — FCFF Approach (Base Year: FY26A)
A3: (₹ Crores unless noted) | B3: FY26A | C3: Yr1E | D3: Yr2E | E3: Yr3E | F3: Yr4E | G3: Yr5E
A5: Revenue | B5: =Assumptions!$B$20 -> 267021 | C5: =B5*(1+Assumptions!$B$22) -> 285712.47 | D5: =C5*(1+Assumptions!$B$23) -> 305712.34 | E5: =D5*(1+Assumptions!$B$24) -> 325583.65 | F5: =E5*(1+Assumptions!$B$25) -> 345118.66 | G5: =F5*(1+Assumptions!$B$26) -> 364100.19
A6: Revenue Growth % | C6: =C5/B5-1 -> 0.07 | D6: =D5/C5-1 -> 0.07 | E6: =E5/D5-1 -> 0.065 | F6: =F5/E5-1 -> 0.06 | G6: =G5/F5-1 -> 0.055
A8: EBIT (Operating Profit) | B8: =B5*Assumptions!$B$21 -> 72362.691 | C8: =C5*Assumptions!$B$21 -> 77428.079 | D8: =D5*Assumptions!$B$21 -> 82848.045 | E8: =E5*Assumptions!$B$21 -> 88233.168 | F8: =F5*Assumptions!$B$21 -> 93527.158 | G8: =G5*Assumptions!$B$21 -> 98671.152
A9: EBIT Margin % | B9: =B8/B5 -> 0.271 | C9: =C8/C5 -> 0.271 | D9: =D8/D5 -> 0.271 | E9: =E8/E5 -> 0.271 | F9: =F8/F5 -> 0.271 | G9: =G8/G5 -> 0.271
A11: Less: Cash Taxes (Effective Rate) | C11: =-C8*Assumptions!$B$6 -> -19357.02 | D11: =-D8*Assumptions!$B$6 -> -20712.011 | E11: =-E8*Assumptions!$B$6 -> -22058.292 | F11: =-F8*Assumptions!$B$6 -> -23381.789 | G11: =-G8*Assumptions!$B$6 -> -24667.788
A12: NOPAT (Net Operating Profit After Tax) | C12: =C8+C11 -> 58071.06 | D12: =D8+D11 -> 62136.034 | E12: =E8+E11 -> 66174.876 | F12: =F8+F11 -> 70145.368 | G12: =G8+G11 -> 74003.364
A14: Add: Depreciation & Amortization | C14: =C5*Assumptions!$B$8 -> 5999.9619 | D14: =D5*Assumptions!$B$8 -> 6419.9592 | E14: =E5*Assumptions!$B$8 -> 6837.2565 | F14: =F5*Assumptions!$B$8 -> 7247.4919 | G14: =G5*Assumptions!$B$8 -> 7646.104
A15: Less: Capital Expenditure | C15: =-C5*Assumptions!$B$9 -> -6285.6743 | D15: =-D5*Assumptions!$B$9 -> -6725.6715 | E15: =-E5*Assumptions!$B$9 -> -7162.8402 | F15: =-F5*Assumptions!$B$9 -> -7592.6106 | G15: =-G5*Assumptions!$B$9 -> -8010.2042
A16: Less: Increase in Net Working Capital | C16: =-(C5-B5)*Assumptions!$B$10 -> -1495.3176 | D16: =-(D5-C5)*Assumptions!$B$10 -> -1599.9898 | E16: =-(E5-D5)*Assumptions!$B$10 -> -1589.7042 | F16: =-(F5-E5)*Assumptions!$B$10 -> -1562.8015 | G16: =-(G5-F5)*Assumptions!$B$10 -> -1518.5221
A18: Unlevered Free Cash Flow (FCFF) | C18: =C12+C14+C15+C16 -> 56290.029 | D18: =D12+D14+D15+D16 -> 60230.332 | E18: =E12+E14+E15+E16 -> 64259.588 | F18: =F12+F14+F15+F16 -> 68237.448 | G18: =G12+G14+G15+G16 -> 72120.741
A20: Discount Period (t) | C20: 1 | D20: 2 | E20: 3 | F20: 4 | G20: 5
A21: Discount Factor @ WACC | C21: =1/(1+Assumptions!$B$36)^C20 -> 0.88993024 | D21: =1/(1+Assumptions!$B$36)^D20 -> 0.79197583 | E21: =1/(1+Assumptions!$B$36)^E20 -> 0.70480324 | F21: =1/(1+Assumptions!$B$36)^F20 -> 0.62722572 | G21: =1/(1+Assumptions!$B$36)^G20 -> 0.55818713
A22: PV of FCFF | C22: =C18*C21 -> 50094.199 | D22: =D18*D21 -> 47700.967 | E22: =E18*E21 -> 45290.366 | F22: =F18*F21 -> 42800.282 | G22: =G18*G21 -> 40256.87
A25: Valuation Summary
A26: Sum of PV of Explicit FCFF (Yr1E-Yr5E) | B26: =SUM(C22:G22) -> 226142.68
A27: Terminal Value (Gordon Growth, end of Yr5E) | B27: =G18*(1+Assumptions!$B$11)/(Assumptions!$B$36-Assumptions!$B$11) -> 1027729.3
A28: PV of Terminal Value | B28: =B27*G21 -> 573665.28
A29: Enterprise Value | B29: =B26+B28 -> 799807.96
A30: Less: Net Debt / (Net Cash) | B30: =Assumptions!$B$31 -> -22705
A31: Equity Value | B31: =B29-B30 -> 822512.96
A32: Shares Outstanding (Cr) | B32: =Assumptions!$B$16 -> 361.8
A33: Implied Value per Share (₹) | B33: =B31/B32 -> 2273.3913
A34: Current Share Price (₹, Jul 2026) | B34: =Assumptions!$B$15 -> 2069
A35: Implied Upside / (Downside) | B35: =B33/B34-1 -> 0.098787467

Sheet DCF - Infosys
A1: Infosys — Discounted Cash Flow (DCF) Model — FCFF Approach (Base Year: FY26A)
A3: (₹ Crores unless noted) | B3: FY26A | C3: Yr1E | D3: Yr2E | E3: Yr3E | F3: Yr4E | G3: Yr5E
A5: Revenue | B5: =Assumptions!$C$20 -> 178650 | C5: =B5*(1+Assumptions!$C$22) -> 192942 | D5: =C5*(1+Assumptions!$C$23) -> 207412.65 | E5: =D5*(1+Assumptions!$C$24) -> 221931.54 | F5: =E5*(1+Assumptions!$C$25) -> 236357.09 | G5: =F5*(1+Assumptions!$C$26) -> 250538.51
A6: Revenue Growth % | C6: =C5/B5-1 -> 0.08 | D6: =D5/C5-1 -> 0.075 | E6: =E5/D5-1 -> 0.07 | F6: =F5/E5-1 -> 0.065 | G6: =G5/F5-1 -> 0.06
A8: EBIT (Operating Profit) | B8: =B5*Assumptions!$C$21 -> 36265.95 | C8: =C5*Assumptions!$C$21 -> 39167.226 | D8: =D5*Assumptions!$C$21 -> 42104.768 | E8: =E5*Assumptions!$C$21 -> 45052.102 | F8: =F5*Assumptions!$C$21 -> 47980.488 | G8: =G5*Assumptions!$C$21 -> 50859.318
A9: EBIT Margin % | B9: =B8/B5 -> 0.203 | C9: =C8/C5 -> 0.203 | D9: =D8/D5 -> 0.203 | E9: =E8/E5 -> 0.203 | F9: =F8/F5 -> 0.203 | G9: =G8/G5 -> 0.203
A11: Less: Cash Taxes (Effective Rate) | C11: =-C8*Assumptions!$B$6 -> -9791.8065 | D11: =-D8*Assumptions!$B$6 -> -10526.192 | E11: =-E8*Assumptions!$B$6 -> -11263.025 | F11: =-F8*Assumptions!$B$6 -> -11995.122 | G11: =-G8*Assumptions!$B$6 -> -12714.829
A12: NOPAT (Net Operating Profit After Tax) | C12: =C8+C11 -> 29375.419 | D12: =D8+D11 -> 31578.576 | E12: =E8+E11 -> 33789.076 | F12: =F8+F11 -> 35985.366 | G12: =G8+G11 -> 38144.488
A14: Add: Depreciation & Amortization | C14: =C5*Assumptions!$B$8 -> 4051.782 | D14: =D5*Assumptions!$B$8 -> 4355.6656 | E14: =E5*Assumptions!$B$8 -> 4660.5622 | F14: =F5*Assumptions!$B$8 -> 4963.4988 | G14: =G5*Assumptions!$B$8 -> 5261.3087
A15: Less: Capital Expenditure | C15: =-C5*Assumptions!$B$9 -> -4244.724 | D15: =-D5*Assumptions!$B$9 -> -4563.0783 | E15: =-E5*Assumptions!$B$9 -> -4882.4938 | F15: =-F5*Assumptions!$B$9 -> -5199.8559 | G15: =-G5*Assumptions!$B$9 -> -5511.8472
A16: Less: Increase in Net Working Capital | C16: =-(C5-B5)*Assumptions!$B$10 -> -1143.36 | D16: =-(D5-C5)*Assumptions!$B$10 -> -1157.652 | E16: =-(E5-D5)*Assumptions!$B$10 -> -1161.5108 | F16: =-(F5-E5)*Assumptions!$B$10 -> -1154.044 | G16: =-(G5-F5)*Assumptions!$B$10 -> -1134.514
A18: Unlevered Free Cash Flow (FCFF) | C18: =C12+C14+C15+C16 -> 28039.118 | D18: =D12+D14+D15+D16 -> 30213.511 | E18: =E12+E14+E15+E16 -> 32405.634 | F18: =F12+F14+F15+F16 -> 34594.965 | G18: =G12+G14+G15+G16 -> 36759.436
A20: Discount Period (t) | C20: 1 | D20: 2 | E20: 3 | F20: 4 | G20: 5
A21: Discount Factor @ WACC | C21: =1/(1+Assumptions!$C$36)^C20 -> 0.88835223 | D21: =1/(1+Assumptions!$C$36)^D20 -> 0.78916969 | E21: =1/(1+Assumptions!$C$36)^E20 -> 0.70106066 | F21: =1/(1+Assumptions!$C$36)^F20 -> 0.6227888 | G21: =1/(1+Assumptions!$C$36)^G20 -> 0.55325582
A22: PV of FCFF | C22: =C18*C21 -> 24908.613 | D22: =D18*D21 -> 23843.587 | E22: =E18*E21 -> 22718.315 | F22: =F18*F21 -> 21545.357 | G22: =G18*G21 -> 20337.372
A25: Valuation Summary
A26: Sum of PV of Explicit FCFF (Yr1E-Yr5E) | B26: =SUM(C22:G22) -> 113353.24
A27: Terminal Value (Gordon Growth, end of Yr5E) | B27: =G18*(1+Assumptions!$B$11)/(Assumptions!$C$36-Assumptions!$B$11) -> 510010.62
A28: PV of Terminal Value | B28: =B27*G21 -> 282166.34
A29: Enterprise Value | B29: =B26+B28 -> 395519.58
A30: Less: Net Debt / (Net Cash) | B30: =Assumptions!$C$31 -> -14000
A31: Equity Value | B31: =B29-B30 -> 409519.58
A32: Shares Outstanding (Cr) | B32: =Assumptions!$C$16 -> 411.6
A33: Implied Value per Share (₹) | B33: =B31/B32 -> 994.94554
A34: Current Share Price (₹, Jul 2026) | B34: =Assumptions!$C$15 -> 1053
A35: Implied Upside / (Downside) | B35: =B33/B34-1 -> -0.05513244

Sheet DCF - HCLTech
A1: HCLTech — Discounted Cash Flow (DCF) Model — FCFF Approach (Base Year: FY26A)
A3: (₹ Crores unless noted) | B3: FY26A | C3: Yr1E | D3: Yr2E | E3: Yr3E | F3: Yr4E | G3: Yr5E
A5: Revenue | B5: =Assumptions!$D$20 -> 130534 | C5: =B5*(1+Assumptions!$D$22) -> 139671.38 | D5: =C5*(1+Assumptions!$D$23) -> 148750.02 | E5: =D5*(1+Assumptions!$D$24) -> 157675.02 | F5: =E5*(1+Assumptions!$D$25) -> 166347.15 | G5: =F5*(1+Assumptions!$D$26) -> 174664.5
A6: Revenue Growth % | C6: =C5/B5-1 -> 0.07 | D6: =D5/C5-1 -> 0.065 | E6: =E5/D5-1 -> 0.06 | F6: =F5/E5-1 -> 0.055 | G6: =G5/F5-1 -> 0.05
A8: EBIT (Operating Profit) | B8: =B5*Assumptions!$D$21 -> 23365.586 | C8: =C5*Assumptions!$D$21 -> 25001.177 | D8: =D5*Assumptions!$D$21 -> 26626.254 | E8: =E5*Assumptions!$D$21 -> 28223.829 | F8: =F5*Assumptions!$D$21 -> 29776.139 | G8: =G5*Assumptions!$D$21 -> 31264.946
A9: EBIT Margin % | B9: =B8/B5 -> 0.179 | C9: =C8/C5 -> 0.179 | D9: =D8/D5 -> 0.179 | E9: =E8/E5 -> 0.179 | F9: =F8/F5 -> 0.179 | G9: =G8/G5 -> 0.179
A11: Less: Cash Taxes (Effective Rate) | C11: =-C8*Assumptions!$B$6 -> -6250.2943 | D11: =-D8*Assumptions!$B$6 -> -6656.5634 | E11: =-E8*Assumptions!$B$6 -> -7055.9572 | F11: =-F8*Assumptions!$B$6 -> -7444.0348 | G11: =-G8*Assumptions!$B$6 -> -7816.2366
A12: NOPAT (Net Operating Profit After Tax) | C12: =C8+C11 -> 18750.883 | D12: =D8+D11 -> 19969.69 | E12: =E8+E11 -> 21167.872 | F12: =F8+F11 -> 22332.104 | G12: =G8+G11 -> 23448.71
A14: Add: Depreciation & Amortization | C14: =C5*Assumptions!$B$8 -> 2933.099 | D14: =D5*Assumptions!$B$8 -> 3123.7504 | E14: =E5*Assumptions!$B$8 -> 3311.1754 | F14: =F5*Assumptions!$B$8 -> 3493.2901 | G14: =G5*Assumptions!$B$8 -> 3667.9546
A15: Less: Capital Expenditure | C15: =-C5*Assumptions!$B$9 -> -3072.7704 | D15: =-D5*Assumptions!$B$9 -> -3272.5004 | E15: =-E5*Assumptions!$B$9 -> -3468.8505 | F15: =-F5*Assumptions!$B$9 -> -3659.6372 | G15: =-G5*Assumptions!$B$9 -> -3842.6191
A16: Less: Increase in Net Working Capital | C16: =-(C5-B5)*Assumptions!$B$10 -> -730.9904 | D16: =-(D5-C5)*Assumptions!$B$10 -> -726.29118 | E16: =-(E5-D5)*Assumptions!$B$10 -> -714.00009 | F16: =-(F5-E5)*Assumptions!$B$10 -> -693.77009 | G16: =-(G5-F5)*Assumptions!$B$10 -> -665.38859
A18: Unlevered Free Cash Flow (FCFF) | C18: =C12+C14+C15+C16 -> 17880.221 | D18: =D12+D14+D15+D16 -> 19094.649 | E18: =E12+E14+E15+E16 -> 20296.196 | F18: =F12+F14+F15+F16 -> 21471.987 | G18: =G12+G14+G15+G16 -> 22608.657
A20: Discount Period (t) | C20: 1 | D20: 2 | E20: 3 | F20: 4 | G20: 5
A21: Discount Factor @ WACC | C21: =1/(1+Assumptions!$D$36)^C20 -> 0.89092262 | D21: =1/(1+Assumptions!$D$36)^D20 -> 0.79374312 | E21: =1/(1+Assumptions!$D$36)^E20 -> 0.7071637 | F21: =1/(1+Assumptions!$D$36)^F20 -> 0.63002814 | G21: =1/(1+Assumptions!$D$36)^G20 -> 0.56130633
A22: PV of FCFF | C22: =C18*C21 -> 15929.893 | D22: =D18*D21 -> 15156.246 | E22: =E18*E21 -> 14352.733 | F22: =F18*F21 -> 13527.956 | G22: =G18*G21 -> 12690.382
A25: Valuation Summary
A26: Sum of PV of Explicit FCFF (Yr1E-Yr5E) | B26: =SUM(C22:G22) -> 71657.211
A27: Terminal Value (Gordon Growth, end of Yr5E) | B27: =G18*(1+Assumptions!$B$11)/(Assumptions!$D$36-Assumptions!$B$11) -> 327743.43
A28: PV of Terminal Value | B28: =B27*G21 -> 183964.46
A29: Enterprise Value | B29: =B26+B28 -> 255621.67
A30: Less: Net Debt / (Net Cash) | B30: =Assumptions!$D$31 -> -9500
A31: Equity Value | B31: =B29-B30 -> 265121.67
A32: Shares Outstanding (Cr) | B32: =Assumptions!$D$16 -> 271.4
A33: Implied Value per Share (₹) | B33: =B31/B32 -> 976.86689
A34: Current Share Price (₹, Jul 2026) | B34: =Assumptions!$D$15 -> 1150
A35: Implied Upside / (Downside) | B35: =B33/B34-1 -> -0.15055053
